{
  "tabs": [
    {
      "id": "windows",
      "label": "Окна",
      "labelKz": "Терезелер",
      "labelEn": "Windows",
      "name": "Окна",
      "nameKz": "Терезелер",
      "nameEn": "Windows",
      "icon": "ri-window-line"
    },
    {
      "id": "appliance",
      "label": "Ремонт бытовой техники",
      "labelKz": "Техника жөндеу",
      "labelEn": "Appliance Repair",
      "name": "Ремонт бытовой техники",
      "nameKz": "Техника жөндеу",
      "nameEn": "Appliance Repair",
      "icon": "ri-tools-line"
    },
    {
      "id": "furniture",
      "label": "Мебель на заказ",
      "labelKz": "Жиһаз жасау",
      "labelEn": "Custom Furniture",
      "name": "Мебель на заказ",
      "nameKz": "Жиһаз жасау",
      "nameEn": "Custom Furniture",
      "icon": "ri-sofa-line"
    },
    {
      "id": "cleaning",
      "label": "Клининг",
      "labelKz": "Тазалау",
      "labelEn": "Cleaning",
      "name": "Клининг",
      "nameKz": "Тазалау",
      "nameEn": "Cleaning",
      "icon": "ri-brush-line"
    }
  ],
  "categories": [
    {
      "id": "cat-app-1",
      "tab": "appliance",
      "title": "Стиральные машины",
      "titleKz": "Кір жуғыш машиналар",
      "titleEn": "Washing Machines",
      "icon": "ri-t-shirt-air-line"
    },
    {
      "id": "cat-app-2",
      "tab": "appliance",
      "title": "Посудомоечные машины",
      "titleKz": "Ыдыс жуғыш машиналар",
      "titleEn": "Dishwashers",
      "icon": "ri-cup-line"
    },
    {
      "id": "cat-app-3",
      "tab": "appliance",
      "title": "Холодильники",
      "titleKz": "Тоңазытқыштар",
      "titleEn": "Refrigerators",
      "icon": "ri-fridge-line"
    },
    {
      "id": "cat-app-4",
      "tab": "appliance",
      "title": "Кондиционеры",
      "titleKz": "Кондиционерлер",
      "titleEn": "Air Conditioners",
      "icon": "ri-temp-cold-line"
    },
    {
      "id": "cat-app-5",
      "tab": "appliance",
      "title": "Сушильные машины",
      "titleKz": "Кептіргіш машиналар",
      "titleEn": "Dryers",
      "icon": "ri-windy-line"
    },
    {
      "id": "cat-app-6",
      "tab": "appliance",
      "title": "Электроплиты и духовки",
      "titleKz": "Электр плиталары мен пештер",
      "titleEn": "Electric Stoves & Ovens",
      "icon": "ri-fire-line"
    },
    {
      "id": "cat-app-7",
      "tab": "appliance",
      "title": "Индукционные и варочные панели",
      "titleKz": "Индукциялық және пісіру панельдері",
      "titleEn": "Induction & Cooktops",
      "icon": "ri-hotspot-line"
    },
    {
      "id": "cat-app-8",
      "tab": "appliance",
      "title": "Вытяжки",
      "titleKz": "Сорғыштар",
      "titleEn": "Range Hoods",
      "icon": "ri-windy-line"
    },
    {
      "id": "cat-win-1",
      "tab": "windows",
      "title": "Москитные сетки",
      "titleKz": "Москитті торлар",
      "titleEn": "Mosquito Nets",
      "icon": "ri-grid-line"
    },
    {
      "id": "cat-win-2",
      "tab": "windows",
      "title": "Плиссе",
      "titleKz": "Плиссе торлары",
      "titleEn": "Plisse Nets",
      "icon": "ri-grid-line"
    },
    {
      "id": "cat-win-3",
      "tab": "windows",
      "title": "Защита от выпадения детей",
      "titleKz": "Балалардың құлауынан қорғау",
      "titleEn": "Child Safety Locks",
      "icon": "ri-shield-check-line"
    },
    {
      "id": "cat-win-4",
      "tab": "windows",
      "title": "Кованые решётки",
      "titleKz": "Соғылған торлар",
      "titleEn": "Wrought Iron Grills",
      "icon": "ri-grid-line"
    },
    {
      "id": "cat-win-5",
      "tab": "windows",
      "title": "Ремонт окон",
      "titleKz": "Терезелерді жөндеу",
      "titleEn": "Window Repair",
      "icon": "ri-tools-line"
    },
    {
      "id": "cat-win-6",
      "tab": "windows",
      "title": "Изготовление окон",
      "titleKz": "Терезелерді дайындау",
      "titleEn": "Window Manufacturing",
      "icon": "ri-building-line"
    },
    {
      "id": "cat-clean-1",
      "tab": "cleaning",
      "title": "Уборка квартир и домов",
      "titleKz": "Пәтерлер мен үйлерді тазалау",
      "titleEn": "House & Apartment Cleaning",
      "icon": "ri-home-4-line"
    },
    {
      "id": "cat-clean-2",
      "tab": "cleaning",
      "title": "Мытьё окон и фасадов",
      "titleKz": "Терезелер мен қасбеттерді жуу",
      "titleEn": "Window & Facade Cleaning",
      "icon": "ri-drop-line"
    },
    {
      "id": "cat-clean-3",
      "tab": "cleaning",
      "title": "Химчистка мебели и покрытий",
      "titleKz": "Жиһаз бен жабындарды химиялық тазалау",
      "titleEn": "Furniture & Carpet Cleaning",
      "icon": "ri-brush-line"
    },
    {
      "id": "cat-clean-4",
      "tab": "cleaning",
      "title": "Коммерческая и спецуборка",
      "titleKz": "Коммерциялық және арнайы тазалау",
      "titleEn": "Commercial & Special Cleaning",
      "icon": "ri-building-4-line"
    },
    {
      "id": "cat-furn-1",
      "tab": "furniture",
      "title": "Мебель на заказ",
      "titleKz": "Жиһаз жасау",
      "titleEn": "Custom Furniture",
      "icon": "ri-sofa-line"
    }
  ],
  "subcategories": {
    "cat-win-1": [
      {
        "id": "sub-win-1-1",
        "title": "Стандартная (рамочная) сетка",
        "titleKz": "Стандартная (рамочная) сетка",
        "titleEn": "Стандартная (рамочная) сетка"
      },
      {
        "id": "sub-win-1-2",
        "title": "Антикошка (усиленная)",
        "titleKz": "Антикошка (усиленная)",
        "titleEn": "Антикошка (усиленная)"
      },
      {
        "id": "sub-win-1-3",
        "title": "Антимошка (мелкая ячейка)",
        "titleKz": "Антимошка (мелкая ячейка)",
        "titleEn": "Антимошка (мелкая ячейка)"
      },
      {
        "id": "sub-win-1-4",
        "title": "Антипыль (для аллергиков)",
        "titleKz": "Антипыль (для аллергиков)",
        "titleEn": "Антипыль (для аллергиков)"
      },
      {
        "id": "sub-win-1-5",
        "title": "Ультравью (повышенная прозрачность)",
        "titleKz": "Ультравью (повышенная прозрачность)",
        "titleEn": "Ультравью (повышенная прозрачность)"
      },
      {
        "id": "sub-win-1-6",
        "title": "Сетка плиссе (раздвижная гармошка)",
        "titleKz": "Сетка плиссе (раздвижная гармошка)",
        "titleEn": "Сетка плиссе (раздвижная гармошка)"
      },
      {
        "id": "sub-win-1-7",
        "title": "Раздвижные / дверные / внутренние сетки",
        "titleKz": "Раздвижные / дверные / внутренние сетки",
        "titleEn": "Раздвижные / дверные / внутренние сетки"
      }
    ],
    "cat-win-2": [
      {
        "id": "sub-win-2-1",
        "title": "Москитная сетка плиссе",
        "titleKz": "Москитная сетка плиссе",
        "titleEn": "Москитная сетка плиссе"
      },
      {
        "id": "sub-win-2-2",
        "title": "Шторы плиссе от солнца",
        "titleKz": "Шторы плиссе от солнца",
        "titleEn": "Шторы плиссе от солнца"
      }
    ],
    "cat-win-3": [
      {
        "id": "sub-win-3-1",
        "title": "Алюминиевая решётка 2-в-1 (сетка + защита)",
        "titleKz": "Алюминиевая решётка 2-в-1 (сетка + защита)",
        "titleEn": "Алюминиевая решётка 2-в-1 (сетка + защита)"
      },
      {
        "id": "sub-win-3-2",
        "title": "Прозрачная решётка из монолитного поликарбоната",
        "titleKz": "Прозрачная решётка из монолитного поликарбоната",
        "titleEn": "Прозрачная решётка из монолитного поликарбоната"
      },
      {
        "id": "sub-win-3-3",
        "title": "Блокираторы и ограничители открывания",
        "titleKz": "Блокираторы и ограничители открывания",
        "titleEn": "Блокираторы и ограничители открывания"
      }
    ],
    "cat-win-4": [
      {
        "id": "sub-win-4-1",
        "title": "Кованые решётки на окна",
        "titleKz": "Кованые решётки на окна",
        "titleEn": "Кованые решётки на окна"
      }
    ],
    "cat-win-5": [
      {
        "id": "sub-win-5-1",
        "title": "Регулировка створок и фурнитуры",
        "titleKz": "Регулировка створок и фурнитуры",
        "titleEn": "Регулировка створок и фурнитуры"
      },
      {
        "id": "sub-win-5-2",
        "title": "Устранение продувания, замена уплотнителя",
        "titleKz": "Устранение продувания, замена уплотнителя",
        "titleEn": "Устранение продувания, замена уплотнителя"
      },
      {
        "id": "sub-win-5-3",
        "title": "Замена ручек, петель, фурнитуры",
        "titleKz": "Замена ручек, петель, фурнитуры",
        "titleEn": "Замена ручек, петель, фурнитуры"
      },
      {
        "id": "sub-win-5-4",
        "title": "Замена стеклопакета",
        "titleKz": "Замена стеклопакета",
        "titleEn": "Замена стеклопакета"
      },
      {
        "id": "sub-win-5-5",
        "title": "Ремонт балконных дверей",
        "titleKz": "Ремонт балконных дверей",
        "titleEn": "Ремонт балконных дверей"
      }
    ],
    "cat-win-6": [
      {
        "id": "sub-win-6-1",
        "title": "Окна для квартир и домов",
        "titleKz": "Окна для квартир и домов",
        "titleEn": "Окна для квартир и домов"
      },
      {
        "id": "sub-win-6-2",
        "title": "Остекление балконов и лоджий",
        "titleKz": "Остекление балконов и лоджий",
        "titleEn": "Остекление балконов и лоджий"
      },
      {
        "id": "sub-win-6-3",
        "title": "Откосы и подоконники",
        "titleKz": "Откосы и подоконники",
        "titleEn": "Откосы и подоконники"
      }
    ],
    "cat-clean-1": [
      {
        "id": "sub-clean-1-1",
        "title": "Поддерживающая уборка",
        "titleKz": "Поддерживающая уборка",
        "titleEn": "Поддерживающая уборка"
      },
      {
        "id": "sub-clean-1-2",
        "title": "Генеральная уборка",
        "titleKz": "Генеральная уборка",
        "titleEn": "Генеральная уборка"
      },
      {
        "id": "sub-clean-1-3",
        "title": "Уборка после ремонта",
        "titleKz": "Уборка после ремонта",
        "titleEn": "Уборка после ремонта"
      },
      {
        "id": "sub-clean-1-4",
        "title": "Уборка после переезда",
        "titleKz": "Уборка после переезда",
        "titleEn": "Уборка после переезда"
      },
      {
        "id": "sub-clean-1-5",
        "title": "Экспресс-уборка (1–2 часа)",
        "titleKz": "Экспресс-уборка (1–2 часа)",
        "titleEn": "Экспресс-уборка (1–2 часа)"
      }
    ],
    "cat-clean-2": [
      {
        "id": "sub-clean-2-1",
        "title": "Мытьё окон",
        "titleKz": "Мытьё окон",
        "titleEn": "Мытьё окон"
      },
      {
        "id": "sub-clean-2-2",
        "title": "Мытьё витрин и фасадов",
        "titleKz": "Мытьё витрин и фасадов",
        "titleEn": "Мытьё витрин и фасадов"
      },
      {
        "id": "sub-clean-2-3",
        "title": "Мытьё балконов и лоджий",
        "titleKz": "Мытьё балконов и лоджий",
        "titleEn": "Мытьё балконов и лоджий"
      },
      {
        "id": "sub-clean-2-4",
        "title": "Чистка жалюзи",
        "titleKz": "Чистка жалюзи",
        "titleEn": "Чистка жалюзи"
      },
      {
        "id": "sub-clean-2-5",
        "title": "Мытьё люстр и светильников",
        "titleKz": "Мытьё люстр и светильников",
        "titleEn": "Мытьё люстр и светильников"
      }
    ],
    "cat-clean-3": [
      {
        "id": "sub-clean-3-1",
        "title": "Химчистка дивана",
        "titleKz": "Химчистка дивана",
        "titleEn": "Химчистка дивана"
      },
      {
        "id": "sub-clean-3-2",
        "title": "Химчистка кресла",
        "titleKz": "Химчистка кресла",
        "titleEn": "Химчистка кресла"
      },
      {
        "id": "sub-clean-3-3",
        "title": "Химчистка матраса",
        "titleKz": "Химчистка матраса",
        "titleEn": "Химчистка матраса"
      },
      {
        "id": "sub-clean-3-4",
        "title": "Химчистка ковра",
        "titleKz": "Химчистка ковра",
        "titleEn": "Химчистка ковра"
      },
      {
        "id": "sub-clean-3-5",
        "title": "Химчистка стульев",
        "titleKz": "Химчистка стульев",
        "titleEn": "Химчистка стульев"
      }
    ],
    "cat-clean-4": [
      {
        "id": "sub-clean-4-1",
        "title": "Уборка офисов",
        "titleKz": "Уборка офисов",
        "titleEn": "Уборка офисов"
      },
      {
        "id": "sub-clean-4-2",
        "title": "Послестроительная уборка",
        "titleKz": "Послестроительная уборка",
        "titleEn": "Послестроительная уборка"
      },
      {
        "id": "sub-clean-4-3",
        "title": "Дезинфекция помещений",
        "titleKz": "Дезинфекция помещений",
        "titleEn": "Дезинфекция помещений"
      },
      {
        "id": "sub-clean-4-4",
        "title": "Уборка подъездов",
        "titleKz": "Уборка подъездов",
        "titleEn": "Уборка подъездов"
      },
      {
        "id": "sub-clean-4-5",
        "title": "Уход за прилегающей территорией",
        "titleKz": "Уход за прилегающей территорией",
        "titleEn": "Уход за прилегающей территорией"
      }
    ],
    "cat-furn-1": [
      {
        "id": "sub-furn-1-1",
        "title": "Кухни на заказ",
        "titleKz": "Кухни на заказ",
        "titleEn": "Кухни на заказ"
      },
      {
        "id": "sub-furn-1-2",
        "title": "Шкафы-купе",
        "titleKz": "Шкафы-купе",
        "titleEn": "Шкафы-купе"
      },
      {
        "id": "sub-furn-1-3",
        "title": "Гардеробные",
        "titleKz": "Гардеробные",
        "titleEn": "Гардеробные"
      },
      {
        "id": "sub-furn-1-4",
        "title": "Прихожие",
        "titleKz": "Прихожие",
        "titleEn": "Прихожие"
      },
      {
        "id": "sub-furn-1-5",
        "title": "Кровати и спальни",
        "titleKz": "Кровати и спальни",
        "titleEn": "Кровати и спальни"
      },
      {
        "id": "sub-furn-1-6",
        "title": "Двухъярусные кровати",
        "titleKz": "Двухъярусные кровати",
        "titleEn": "Двухъярусные кровати"
      },
      {
        "id": "sub-furn-1-7",
        "title": "Детская мебель",
        "titleKz": "Детская мебель",
        "titleEn": "Детская мебель"
      },
      {
        "id": "sub-furn-1-8",
        "title": "Комоды и тумбы",
        "titleKz": "Комоды и тумбы",
        "titleEn": "Комоды и тумбы"
      },
      {
        "id": "sub-furn-1-9",
        "title": "Столы и стулья",
        "titleKz": "Столы и стулья",
        "titleEn": "Столы и стулья"
      },
      {
        "id": "sub-furn-1-10",
        "title": "Мебель для ванной",
        "titleKz": "Мебель для ванной",
        "titleEn": "Мебель для ванной"
      },
      {
        "id": "sub-furn-1-11",
        "title": "Торговая и офисная мебель",
        "titleKz": "Торговая и офисная мебель",
        "titleEn": "Торговая и офисная мебель"
      },
      {
        "id": "sub-furn-1-12",
        "title": "Мягкая мебель на заказ",
        "titleKz": "Мягкая мебель на заказ",
        "titleEn": "Мягкая мебель на заказ"
      }
    ],
    "cat-app-1": [
      {
        "id": "sub-app-1-1",
        "title": "Диагностика",
        "titleKz": "Диагностика",
        "titleEn": "Диагностика"
      },
      {
        "id": "sub-app-1-2",
        "title": "Замена подшипников",
        "titleKz": "Замена подшипников",
        "titleEn": "Замена подшипников"
      },
      {
        "id": "sub-app-1-3",
        "title": "Замена ТЭНа",
        "titleKz": "Замена ТЭНа",
        "titleEn": "Замена ТЭНа"
      },
      {
        "id": "sub-app-1-4",
        "title": "Замена насоса (помпы)",
        "titleKz": "Замена насоса (помпы)",
        "titleEn": "Замена насоса (помпы)"
      },
      {
        "id": "sub-app-1-5",
        "title": "Замена ремня",
        "titleKz": "Замена ремня",
        "titleEn": "Замена ремня"
      },
      {
        "id": "sub-app-1-6",
        "title": "Ремонт электронного модуля",
        "titleKz": "Ремонт электронного модуля",
        "titleEn": "Ремонт электронного модуля"
      },
      {
        "id": "sub-app-1-7",
        "title": "Замена амортизаторов",
        "titleKz": "Замена амортизаторов",
        "titleEn": "Замена амортизаторов"
      },
      {
        "id": "sub-app-1-8",
        "title": "Устранение засора",
        "titleKz": "Устранение засора",
        "titleEn": "Устранение засора"
      }
    ],
    "cat-app-2": [
      {
        "id": "sub-app-2-1",
        "title": "Диагностика",
        "titleKz": "Диагностика",
        "titleEn": "Диагностика"
      },
      {
        "id": "sub-app-2-2",
        "title": "Замена ТЭНа",
        "titleKz": "Замена ТЭНа",
        "titleEn": "Замена ТЭНа"
      },
      {
        "id": "sub-app-2-3",
        "title": "Замена насоса",
        "titleKz": "Замена насоса",
        "titleEn": "Замена насоса"
      },
      {
        "id": "sub-app-2-4",
        "title": "Устранение засора",
        "titleKz": "Устранение засора",
        "titleEn": "Устранение засора"
      },
      {
        "id": "sub-app-2-5",
        "title": "Ремонт модуля управления",
        "titleKz": "Ремонт модуля управления",
        "titleEn": "Ремонт модуля управления"
      },
      {
        "id": "sub-app-2-6",
        "title": "Замена заливного/сливного клапана",
        "titleKz": "Замена заливного/сливного клапана",
        "titleEn": "Замена заливного/сливного клапана"
      },
      {
        "id": "sub-app-2-7",
        "title": "Устранение протечки",
        "titleKz": "Устранение протечки",
        "titleEn": "Устранение протечки"
      }
    ],
    "cat-app-3": [
      {
        "id": "sub-app-3-1",
        "title": "Диагностика",
        "titleKz": "Диагностика",
        "titleEn": "Диагностика"
      },
      {
        "id": "sub-app-3-2",
        "title": "Заправка фреоном",
        "titleKz": "Заправка фреоном",
        "titleEn": "Заправка фреоном"
      },
      {
        "id": "sub-app-3-3",
        "title": "Замена компрессора",
        "titleKz": "Замена компрессора",
        "titleEn": "Замена компрессора"
      },
      {
        "id": "sub-app-3-4",
        "title": "Замена терморегулятора",
        "titleKz": "Замена терморегулятора",
        "titleEn": "Замена терморегулятора"
      },
      {
        "id": "sub-app-3-5",
        "title": "Замена уплотнительной резины",
        "titleKz": "Замена уплотнительной резины",
        "titleEn": "Замена уплотнительной резины"
      },
      {
        "id": "sub-app-3-6",
        "title": "Ремонт системы No Frost",
        "titleKz": "Ремонт системы No Frost",
        "titleEn": "Ремонт системы No Frost"
      },
      {
        "id": "sub-app-3-7",
        "title": "Замена платы управления",
        "titleKz": "Замена платы управления",
        "titleEn": "Замена платы управления"
      }
    ],
    "cat-app-4": [
      {
        "id": "sub-app-4-1",
        "title": "Диагностика",
        "titleKz": "Диагностика",
        "titleEn": "Диагностика"
      },
      {
        "id": "sub-app-4-2",
        "title": "Заправка фреоном",
        "titleKz": "Заправка фреоном",
        "titleEn": "Заправка фреоном"
      },
      {
        "id": "sub-app-4-3",
        "title": "Чистка и обслуживание",
        "titleKz": "Чистка и обслуживание",
        "titleEn": "Чистка и обслуживание"
      },
      {
        "id": "sub-app-4-4",
        "title": "Установка / монтаж",
        "titleKz": "Установка / монтаж",
        "titleEn": "Установка / монтаж"
      },
      {
        "id": "sub-app-4-5",
        "title": "Демонтаж",
        "titleKz": "Демонтаж",
        "titleEn": "Демонтаж"
      },
      {
        "id": "sub-app-4-6",
        "title": "Ремонт платы",
        "titleKz": "Ремонт платы",
        "titleEn": "Ремонт платы"
      },
      {
        "id": "sub-app-4-7",
        "title": "Замена компрессора",
        "titleKz": "Замена компрессора",
        "titleEn": "Замена компрессора"
      }
    ],
    "cat-app-5": [
      {
        "id": "sub-app-5-1",
        "title": "Диагностика",
        "titleKz": "Диагностика",
        "titleEn": "Диагностика"
      },
      {
        "id": "sub-app-5-2",
        "title": "Замена ТЭНа",
        "titleKz": "Замена ТЭНа",
        "titleEn": "Замена ТЭНа"
      },
      {
        "id": "sub-app-5-3",
        "title": "Замена ремня",
        "titleKz": "Замена ремня",
        "titleEn": "Замена ремня"
      },
      {
        "id": "sub-app-5-4",
        "title": "Чистка фильтров и каналов",
        "titleKz": "Чистка фильтров и каналов",
        "titleEn": "Чистка фильтров и каналов"
      },
      {
        "id": "sub-app-5-5",
        "title": "Ремонт модуля",
        "titleKz": "Ремонт модуля",
        "titleEn": "Ремонт модуля"
      },
      {
        "id": "sub-app-5-6",
        "title": "Замена подшипников",
        "titleKz": "Замена подшипников",
        "titleEn": "Замена подшипников"
      }
    ],
    "cat-app-6": [
      {
        "id": "sub-app-6-1",
        "title": "Диагностика",
        "titleKz": "Диагностика",
        "titleEn": "Диагностика"
      },
      {
        "id": "sub-app-6-2",
        "title": "Замена ТЭНа духовки",
        "titleKz": "Замена ТЭНа духовки",
        "titleEn": "Замена ТЭНа духовки"
      },
      {
        "id": "sub-app-6-3",
        "title": "Замена конфорки",
        "titleKz": "Замена конфорки",
        "titleEn": "Замена конфорки"
      },
      {
        "id": "sub-app-6-4",
        "title": "Замена термостата",
        "titleKz": "Замена термостата",
        "titleEn": "Замена термостата"
      },
      {
        "id": "sub-app-6-5",
        "title": "Ремонт переключателей",
        "titleKz": "Ремонт переключателей",
        "titleEn": "Ремонт переключателей"
      },
      {
        "id": "sub-app-6-6",
        "title": "Замена стекла дверцы",
        "titleKz": "Замена стекла дверцы",
        "titleEn": "Замена стекла дверцы"
      }
    ],
    "cat-app-7": [
      {
        "id": "sub-app-7-1",
        "title": "Диагностика",
        "titleKz": "Диагностика",
        "titleEn": "Диагностика"
      },
      {
        "id": "sub-app-7-2",
        "title": "Замена стеклокерамики",
        "titleKz": "Замена стеклокерамики",
        "titleEn": "Замена стеклокерамики"
      },
      {
        "id": "sub-app-7-3",
        "title": "Ремонт силового модуля",
        "titleKz": "Ремонт силового модуля",
        "titleEn": "Ремонт силового модуля"
      },
      {
        "id": "sub-app-7-4",
        "title": "Замена катушки индукции",
        "titleKz": "Замена катушки индукции",
        "titleEn": "Замена катушки индукции"
      },
      {
        "id": "sub-app-7-5",
        "title": "Замена сенсорной панели",
        "titleKz": "Замена сенсорной панели",
        "titleEn": "Замена сенсорной панели"
      },
      {
        "id": "sub-app-7-6",
        "title": "Устранение ошибок (коды E)",
        "titleKz": "Устранение ошибок (коды E)",
        "titleEn": "Устранение ошибок (коды E)"
      }
    ],
    "cat-app-8": [
      {
        "id": "sub-app-8-1",
        "title": "Диагностика",
        "titleKz": "Диагностика",
        "titleEn": "Диагностика"
      },
      {
        "id": "sub-app-8-2",
        "title": "Замена двигателя",
        "titleKz": "Замена двигателя",
        "titleEn": "Замена двигателя"
      },
      {
        "id": "sub-app-8-3",
        "title": "Ремонт/замена подсветки",
        "titleKz": "Ремонт/замена подсветки",
        "titleEn": "Ремонт/замена подсветки"
      },
      {
        "id": "sub-app-8-4",
        "title": "Чистка и обслуживание",
        "titleKz": "Чистка и обслуживание",
        "titleEn": "Чистка и обслуживание"
      },
      {
        "id": "sub-app-8-5",
        "title": "Замена фильтров",
        "titleKz": "Замена фильтров",
        "titleEn": "Замена фильтров"
      },
      {
        "id": "sub-app-8-6",
        "title": "Ремонт кнопок/электроники",
        "titleKz": "Ремонт кнопок/электроники",
        "titleEn": "Ремонт кнопок/электроники"
      }
    ]
  },
  "details": {
    "sub-win-1-1": {
      "title": "Стандартная (рамочная) сетка",
      "desc": "Компактный замок с тросиком или защелкой, который позволяет проветривать помещение, но не дает окну открыться полностью. Идеальная защита для детей.",
      "price": "от 2 500 ₸",
      "time": "Срок: 30 мин",
      "warr": "Гарантия: 12 мес",
      "image": ""
    },
    "sub-win-1-2": {
      "title": "Антикошка (усиленная)",
      "desc": "Замена стандартной оконной ручки на ручку со встроенным замком. Окно фиксируется ключом в закрытом или откинутом положении.",
      "price": "от 3 500 ₸",
      "time": "Срок: 30 мин",
      "warr": "Гарантия: 12 мес",
      "image": ""
    },
    "sub-win-1-3": {
      "title": "Антимошка (мелкая ячейка)",
      "desc": "Позволяет зафиксировать створку окна с зазором от 10 до 70 мм. Простой и надежный механизм.",
      "price": "от 1 500 ₸",
      "time": "Срок: 20 мин",
      "warr": "Гарантия: 6 мес",
      "image": ""
    },
    "sub-win-1-4": {
      "title": "Антипыль (для аллергиков)",
      "desc": "Усиленные блокираторы поворота створки (флажковые замки). Выдерживают высокие нагрузки и исключают выпадение.",
      "price": "от 3 000 ₸",
      "time": "Срок: 30 мин",
      "warr": "Гарантия: 12 мес",
      "image": ""
    },
    "sub-win-1-5": {
      "title": "Ультравью (повышенная прозрачность)",
      "desc": "Профессиональные услуги: Ультравью (повышенная прозрачность) в Алматы и по всему Казахстану. Быстрый выезд, квалифицированные специалисты и гарантия качества.",
      "price": "Договорная цена",
      "time": "Выезд: 45 мин",
      "warr": "Гарантия: 12 мес"
    },
    "sub-win-1-6": {
      "title": "Сетка плиссе (раздвижная гармошка)",
      "desc": "Профессиональные услуги: Сетка плиссе (раздвижная гармошка) в Алматы и по всему Казахстану. Быстрый выезд, квалифицированные специалисты и гарантия качества.",
      "price": "Договорная цена",
      "time": "Выезд: 45 мин",
      "warr": "Гарантия: 12 мес"
    },
    "sub-win-1-7": {
      "title": "Раздвижные / дверные / внутренние сетки",
      "desc": "Профессиональные услуги: Раздвижные / дверные / внутренние сетки в Алматы и по всему Казахстану. Быстрый выезд, квалифицированные специалисты и гарантия качества.",
      "price": "Договорная цена",
      "time": "Выезд: 45 мин",
      "warr": "Гарантия: 12 мес"
    },
    "sub-win-2-1": {
      "title": "Москитная сетка плиссе",
      "desc": "Замки с ключом на створки окон, предотвращающие открывание створки детьми.",
      "price": "от 2 000 ₸",
      "time": "Срок: 30 мин",
      "warr": "Гарантия: 12 мес"
    },
    "sub-win-2-2": {
      "title": "Шторы плиссе от солнца",
      "desc": "Безопасные открывающиеся или раздвижные решетки на окна для защиты от выпадения и взлома.",
      "price": "от 5 000 ₸",
      "time": "Срок: 2-3 часа",
      "warr": "Гарантия: 12 мес"
    },
    "sub-win-3-1": {
      "title": "Алюминиевая решётка 2-в-1 (сетка + защита)",
      "desc": "Кованые решетки на окна — надежная защита от взлома и украшение фасада. Элементы художественной ковки ручной работы и качественные отделочные материалы. Полотно — стальной прут, рисунок — любой, полимерная покраска (стандарт — черный). Изготовление по размеру проема.",
      "price": "от 15 000 ₸",
      "time": "Срок: 3 дня",
      "warr": "Гарантия: 12 мес",
      "image": ""
    },
    "sub-win-3-2": {
      "title": "Прозрачная решётка из монолитного поликарбоната",
      "desc": "Срочное изготовление и замена разбитых или треснувших однокамерных, двухкамерных стеклопакетов.",
      "price": "от 10 000 ₸",
      "time": "Срок: 2 часа",
      "warr": "Гарантия: 12 мес"
    },
    "sub-win-3-3": {
      "title": "Блокираторы и ограничители открывания",
      "desc": "Замена изношенного оконного резинового уплотнителя на качественный немецкий (KBE, Rehau) для полной герметизации.",
      "price": "от 1 000 ₸/п.м",
      "time": "Срок: 1 час",
      "warr": "Гарантия: 12 мес"
    },
    "sub-win-4-1": {
      "title": "Кованые решётки на окна",
      "desc": "Москитная сетка «Антикошка» с усиленным полотном Pet Screen (ячейка около 0,6×1,8 мм) повышенной прочности. Устойчива к когтям кошек и собак, не рвется, задерживает крупных насекомых, мелкую пыль и аллергены. Алюминиевая рамка (цвета: белый, коричневый, антрацит, под заказ — любой), усиленные крепления. Защищает питомцев от выпадения и от насекомых. Изготовление по размеру проема.",
      "price": "от 12 000 ₸",
      "time": "Срок: 1-3 дня",
      "warr": "Гарантия: 12 мес",
      "image": ""
    },
    "sub-win-5-1": {
      "title": "Регулировка створок и фурнитуры",
      "desc": "Большой выбор тканей (блэкаут, день-ночь, принты). Точный замер и качественная установка.",
      "price": "от 5 000 ₸",
      "time": "Срок: 2-3 дня",
      "warr": "Гарантия: 12 мес"
    },
    "sub-win-5-2": {
      "title": "Устранение продувания, замена уплотнителя",
      "desc": "Классические алюминиевые и пластиковые горизонтальные жалюзи разных цветов для офиса и дома.",
      "price": "от 4 000 ₸",
      "time": "Срок: 1-2 дня",
      "warr": "Гарантия: 12 мес"
    },
    "sub-win-5-3": {
      "title": "Замена ручек, петель, фурнитуры",
      "desc": "Тканевые и пластиковые вертикальные жалюзи любой высоты. Отлично подходят для больших окон.",
      "price": "от 4 500 ₸",
      "time": "Срок: 2-3 дня",
      "warr": "Гарантия: 12 мес"
    },
    "sub-win-5-4": {
      "title": "Замена стеклопакета",
      "desc": "Профессиональные услуги: Замена стеклопакета в Алматы и по всему Казахстану. Быстрый выезд, квалифицированные специалисты и гарантия качества.",
      "price": "Договорная цена",
      "time": "Выезд: 45 мин",
      "warr": "Гарантия: 12 мес"
    },
    "sub-win-5-5": {
      "title": "Ремонт балконных дверей",
      "desc": "Профессиональные услуги: Ремонт балконных дверей в Алматы и по всему Казахстану. Быстрый выезд, квалифицированные специалисты и гарантия качества.",
      "price": "Договорная цена",
      "time": "Выезд: 45 мин",
      "warr": "Гарантия: 12 мес"
    },
    "sub-win-6-1": {
      "title": "Окна для квартир и домов",
      "desc": "Профессиональные услуги: Окна для квартир и домов в Алматы и по всему Казахстану. Быстрый выезд, квалифицированные специалисты и гарантия качества.",
      "price": "Договорная цена",
      "time": "Выезд: 45 мин",
      "warr": "Гарантия: 12 мес"
    },
    "sub-win-6-2": {
      "title": "Остекление балконов и лоджий",
      "desc": "Профессиональные услуги: Остекление балконов и лоджий в Алматы и по всему Казахстану. Быстрый выезд, квалифицированные специалисты и гарантия качества.",
      "price": "Договорная цена",
      "time": "Выезд: 45 мин",
      "warr": "Гарантия: 12 мес"
    },
    "sub-win-6-3": {
      "title": "Откосы и подоконники",
      "desc": "Профессиональные услуги: Откосы и подоконники в Алматы и по всему Казахстану. Быстрый выезд, квалифицированные специалисты и гарантия качества.",
      "price": "Договорная цена",
      "time": "Выезд: 45 мин",
      "warr": "Гарантия: 12 мес"
    },
    "sub-clean-1-1": {
      "title": "Поддерживающая уборка",
      "desc": "Профессиональные услуги: Поддерживающая уборка в Алматы и по всему Казахстану. Быстрый выезд, квалифицированные специалисты и гарантия качества.",
      "price": "Договорная цена",
      "time": "Выезд: 45 мин",
      "warr": "Гарантия: 12 мес"
    },
    "sub-clean-1-2": {
      "title": "Генеральная уборка",
      "desc": "Профессиональные услуги: Генеральная уборка в Алматы и по всему Казахстану. Быстрый выезд, квалифицированные специалисты и гарантия качества.",
      "price": "Договорная цена",
      "time": "Выезд: 45 мин",
      "warr": "Гарантия: 12 мес"
    },
    "sub-clean-1-3": {
      "title": "Уборка после ремонта",
      "desc": "Профессиональные услуги: Уборка после ремонта в Алматы и по всему Казахстану. Быстрый выезд, квалифицированные специалисты и гарантия качества.",
      "price": "Договорная цена",
      "time": "Выезд: 45 мин",
      "warr": "Гарантия: 12 мес"
    },
    "sub-clean-1-4": {
      "title": "Уборка после переезда",
      "desc": "Профессиональные услуги: Уборка после переезда в Алматы и по всему Казахстану. Быстрый выезд, квалифицированные специалисты и гарантия качества.",
      "price": "Договорная цена",
      "time": "Выезд: 45 мин",
      "warr": "Гарантия: 12 мес"
    },
    "sub-clean-1-5": {
      "title": "Экспресс-уборка (1–2 часа)",
      "desc": "Профессиональные услуги: Экспресс-уборка (1–2 часа) в Алматы и по всему Казахстану. Быстрый выезд, квалифицированные специалисты и гарантия качества.",
      "price": "Договорная цена",
      "time": "Выезд: 45 мин",
      "warr": "Гарантия: 12 мес"
    },
    "sub-clean-2-1": {
      "title": "Мытьё окон",
      "desc": "Профессиональные услуги: Мытьё окон в Алматы и по всему Казахстану. Быстрый выезд, квалифицированные специалисты и гарантия качества.",
      "price": "Договорная цена",
      "time": "Выезд: 45 мин",
      "warr": "Гарантия: 12 мес"
    },
    "sub-clean-2-2": {
      "title": "Мытьё витрин и фасадов",
      "desc": "Профессиональные услуги: Мытьё витрин и фасадов в Алматы и по всему Казахстану. Быстрый выезд, квалифицированные специалисты и гарантия качества.",
      "price": "Договорная цена",
      "time": "Выезд: 45 мин",
      "warr": "Гарантия: 12 мес"
    },
    "sub-clean-2-3": {
      "title": "Мытьё балконов и лоджий",
      "desc": "Профессиональные услуги: Мытьё балконов и лоджий в Алматы и по всему Казахстану. Быстрый выезд, квалифицированные специалисты и гарантия качества.",
      "price": "Договорная цена",
      "time": "Выезд: 45 мин",
      "warr": "Гарантия: 12 мес"
    },
    "sub-clean-2-4": {
      "title": "Чистка жалюзи",
      "desc": "Профессиональные услуги: Чистка жалюзи в Алматы и по всему Казахстану. Быстрый выезд, квалифицированные специалисты и гарантия качества.",
      "price": "Договорная цена",
      "time": "Выезд: 45 мин",
      "warr": "Гарантия: 12 мес"
    },
    "sub-clean-2-5": {
      "title": "Мытьё люстр и светильников",
      "desc": "Профессиональные услуги: Мытьё люстр и светильников в Алматы и по всему Казахстану. Быстрый выезд, квалифицированные специалисты и гарантия качества.",
      "price": "Договорная цена",
      "time": "Выезд: 45 мин",
      "warr": "Гарантия: 12 мес"
    },
    "sub-clean-3-1": {
      "title": "Химчистка дивана",
      "desc": "Профессиональные услуги: Химчистка дивана в Алматы и по всему Казахстану. Быстрый выезд, квалифицированные специалисты и гарантия качества.",
      "price": "Договорная цена",
      "time": "Выезд: 45 мин",
      "warr": "Гарантия: 12 мес"
    },
    "sub-clean-3-2": {
      "title": "Химчистка кресла",
      "desc": "Профессиональные услуги: Химчистка кресла в Алматы и по всему Казахстану. Быстрый выезд, квалифицированные специалисты и гарантия качества.",
      "price": "Договорная цена",
      "time": "Выезд: 45 мин",
      "warr": "Гарантия: 12 мес"
    },
    "sub-clean-3-3": {
      "title": "Химчистка матраса",
      "desc": "Профессиональные услуги: Химчистка матраса в Алматы и по всему Казахстану. Быстрый выезд, квалифицированные специалисты и гарантия качества.",
      "price": "Договорная цена",
      "time": "Выезд: 45 мин",
      "warr": "Гарантия: 12 мес"
    },
    "sub-clean-3-4": {
      "title": "Химчистка ковра",
      "desc": "Профессиональные услуги: Химчистка ковра в Алматы и по всему Казахстану. Быстрый выезд, квалифицированные специалисты и гарантия качества.",
      "price": "Договорная цена",
      "time": "Выезд: 45 мин",
      "warr": "Гарантия: 12 мес"
    },
    "sub-clean-3-5": {
      "title": "Химчистка стульев",
      "desc": "Профессиональные услуги: Химчистка стульев в Алматы и по всему Казахстану. Быстрый выезд, квалифицированные специалисты и гарантия качества.",
      "price": "Договорная цена",
      "time": "Выезд: 45 мин",
      "warr": "Гарантия: 12 мес"
    },
    "sub-clean-4-1": {
      "title": "Уборка офисов",
      "desc": "Профессиональные услуги: Уборка офисов в Алматы и по всему Казахстану. Быстрый выезд, квалифицированные специалисты и гарантия качества.",
      "price": "Договорная цена",
      "time": "Выезд: 45 мин",
      "warr": "Гарантия: 12 мес"
    },
    "sub-clean-4-2": {
      "title": "Послестроительная уборка",
      "desc": "Профессиональные услуги: Послестроительная уборка в Алматы и по всему Казахстану. Быстрый выезд, квалифицированные специалисты и гарантия качества.",
      "price": "Договорная цена",
      "time": "Выезд: 45 мин",
      "warr": "Гарантия: 12 мес"
    },
    "sub-clean-4-3": {
      "title": "Дезинфекция помещений",
      "desc": "Профессиональные услуги: Дезинфекция помещений в Алматы и по всему Казахстану. Быстрый выезд, квалифицированные специалисты и гарантия качества.",
      "price": "Договорная цена",
      "time": "Выезд: 45 мин",
      "warr": "Гарантия: 12 мес"
    },
    "sub-clean-4-4": {
      "title": "Уборка подъездов",
      "desc": "Профессиональные услуги: Уборка подъездов в Алматы и по всему Казахстану. Быстрый выезд, квалифицированные специалисты и гарантия качества.",
      "price": "Договорная цена",
      "time": "Выезд: 45 мин",
      "warr": "Гарантия: 12 мес"
    },
    "sub-clean-4-5": {
      "title": "Уход за прилегающей территорией",
      "desc": "Профессиональные услуги: Уход за прилегающей территорией в Алматы и по всему Казахстану. Быстрый выезд, квалифицированные специалисты и гарантия качества.",
      "price": "Договорная цена",
      "time": "Выезд: 45 мин",
      "warr": "Гарантия: 12 мес"
    },
    "sub-furn-1-1": {
      "title": "Кухни на заказ",
      "desc": "Профессиональная сборка кухонных гарнитуров любой сложности. Врезка моек, варочных панелей, подключение подсветки.",
      "price": "от 15 000 ₸",
      "time": "Срок: 1 день",
      "warr": "Гарантия: 12 мес",
      "image": "https://images.unsplash.com/photo-1555041469-a586c61ea9bc?q=80&w=600"
    },
    "sub-furn-1-2": {
      "title": "Шкафы-купе",
      "desc": "Быстрая и аккуратная сборка шкафов-купе, установка дверей, регулировка направляющих.",
      "price": "от 8 000 ₸",
      "time": "Срок: 2-3 часа",
      "warr": "Гарантия: 12 мес",
      "image": "https://images.unsplash.com/photo-1555041469-a586c61ea9bc?q=80&w=600"
    },
    "sub-furn-1-3": {
      "title": "Гардеробные",
      "desc": "Сборка двуспальных, детских, двухъярусных кроватей и диванов любых конструкций.",
      "price": "от 5 000 ₸",
      "time": "Срок: 1-2 часа",
      "warr": "Гарантия: 12 мес",
      "image": "https://images.unsplash.com/photo-1555041469-a586c61ea9bc?q=80&w=600"
    },
    "sub-furn-1-4": {
      "title": "Прихожие",
      "desc": "Аккуратный демонтаж и упаковка мебели перед переездом для сохранения ее целостности.",
      "price": "от 6 000 ₸",
      "time": "Срок: от 2 часов",
      "warr": "Гарантия: -",
      "image": "https://images.unsplash.com/photo-1555041469-a586c61ea9bc?q=80&w=600"
    },
    "sub-furn-1-5": {
      "title": "Кровати и спальни",
      "desc": "Замена обивки диванов, кресел, стульев (ткань, кожа, велюр), ремонт каркаса, замена поролона и пружинных блоков.",
      "price": "от 15 000 ₸",
      "time": "Срок: 2-5 дней",
      "warr": "Гарантия: 12 мес"
    },
    "sub-furn-1-6": {
      "title": "Двухъярусные кровати",
      "desc": "Профессиональные услуги: Двухъярусные кровати в Алматы и по всему Казахстану. Быстрый выезд, квалифицированные специалисты и гарантия качества.",
      "price": "Договорная цена",
      "time": "Выезд: 45 мин",
      "warr": "Гарантия: 12 мес"
    },
    "sub-furn-1-7": {
      "title": "Детская мебель",
      "desc": "Профессиональные услуги: Детская мебель в Алматы и по всему Казахстану. Быстрый выезд, квалифицированные специалисты и гарантия качества.",
      "price": "Договорная цена",
      "time": "Выезд: 45 мин",
      "warr": "Гарантия: 12 мес"
    },
    "sub-furn-1-8": {
      "title": "Комоды и тумбы",
      "desc": "Профессиональные услуги: Комоды и тумбы в Алматы и по всему Казахстану. Быстрый выезд, квалифицированные специалисты и гарантия качества.",
      "price": "Договорная цена",
      "time": "Выезд: 45 мин",
      "warr": "Гарантия: 12 мес"
    },
    "sub-furn-1-9": {
      "title": "Столы и стулья",
      "desc": "Профессиональные услуги: Столы и стулья в Алматы и по всему Казахстану. Быстрый выезд, квалифицированные специалисты и гарантия качества.",
      "price": "Договорная цена",
      "time": "Выезд: 45 мин",
      "warr": "Гарантия: 12 мес"
    },
    "sub-furn-1-10": {
      "title": "Мебель для ванной",
      "desc": "Профессиональные услуги: Мебель для ванной в Алматы и по всему Казахстану. Быстрый выезд, квалифицированные специалисты и гарантия качества.",
      "price": "Договорная цена",
      "time": "Выезд: 45 мин",
      "warr": "Гарантия: 12 мес"
    },
    "sub-furn-1-11": {
      "title": "Торговая и офисная мебель",
      "desc": "Профессиональные услуги: Торговая и офисная мебель в Алматы и по всему Казахстану. Быстрый выезд, квалифицированные специалисты и гарантия качества.",
      "price": "Договорная цена",
      "time": "Выезд: 45 мин",
      "warr": "Гарантия: 12 мес"
    },
    "sub-furn-1-12": {
      "title": "Мягкая мебель на заказ",
      "desc": "Профессиональные услуги: Мягкая мебель на заказ в Алматы и по всему Казахстану. Быстрый выезд, квалифицированные специалисты и гарантия качества.",
      "price": "Договорная цена",
      "time": "Выезд: 45 мин",
      "warr": "Гарантия: 12 мес"
    },
    "sub-app-1-1": {
      "title": "Диагностика",
      "desc": "Замена сгоревшего нагревательного элемента стиральной машины на новый оригинальный ТЭН.",
      "price": "от 6 000 ₸",
      "time": "Срок: 1 час",
      "warr": "Гарантия: 12 мес"
    },
    "sub-app-1-2": {
      "title": "Замена подшипников",
      "desc": "Полный разбор бака стиральной машины и замена изношенных гудящих подшипников и сальника.",
      "price": "от 12 000 ₸",
      "time": "Срок: 3 часа",
      "warr": "Гарантия: 12 мес"
    },
    "sub-app-1-3": {
      "title": "Замена ТЭНа",
      "desc": "Замена неисправной сливной помпы, если машина не сливает воду или выдает ошибку.",
      "price": "от 5 000 ₸",
      "time": "Срок: 45 мин",
      "warr": "Гарантия: 12 мес"
    },
    "sub-app-1-4": {
      "title": "Замена насоса (помпы)",
      "desc": "Прошивка процессора, замена сгоревших реле, симисторов и других элементов на электронной плате управления.",
      "price": "от 8 000 ₸",
      "time": "Срок: 1-2 дня",
      "warr": "Гарантия: 12 мес"
    },
    "sub-app-1-5": {
      "title": "Замена ремня",
      "desc": "Профессиональные услуги: Замена ремня в Алматы и по всему Казахстану. Быстрый выезд, квалифицированные специалисты и гарантия качества.",
      "price": "Договорная цена",
      "time": "Выезд: 45 мин",
      "warr": "Гарантия: 12 мес"
    },
    "sub-app-1-6": {
      "title": "Ремонт электронного модуля",
      "desc": "Профессиональные услуги: Ремонт электронного модуля в Алматы и по всему Казахстану. Быстрый выезд, квалифицированные специалисты и гарантия качества.",
      "price": "Договорная цена",
      "time": "Выезд: 45 мин",
      "warr": "Гарантия: 12 мес"
    },
    "sub-app-1-7": {
      "title": "Замена амортизаторов",
      "desc": "Профессиональные услуги: Замена амортизаторов в Алматы и по всему Казахстану. Быстрый выезд, квалифицированные специалисты и гарантия качества.",
      "price": "Договорная цена",
      "time": "Выезд: 45 мин",
      "warr": "Гарантия: 12 мес"
    },
    "sub-app-1-8": {
      "title": "Устранение засора",
      "desc": "Профессиональные услуги: Устранение засора в Алматы и по всему Казахстану. Быстрый выезд, квалифицированные специалисты и гарантия качества.",
      "price": "Договорная цена",
      "time": "Выезд: 45 мин",
      "warr": "Гарантия: 12 мес"
    },
    "sub-app-2-1": {
      "title": "Диагностика",
      "desc": "Вакуумирование системы и точная заправка хладагентом (R134a, R600a) по весам с устранением утечки.",
      "price": "от 7 000 ₸",
      "time": "Срок: 1 час",
      "warr": "Гарантия: 12 мес"
    },
    "sub-app-2-2": {
      "title": "Замена ТЭНа",
      "desc": "Демонтаж старого мотора, установка нового мотор-компрессора, замена фильтра-осушителя и заправка фреоном.",
      "price": "от 18 000 ₸",
      "time": "Срок: 2 часа",
      "warr": "Гарантия: 12 мес"
    },
    "sub-app-2-3": {
      "title": "Замена насоса",
      "desc": "Замена механического терморегулятора или датчика температуры холодильной/морозильной камеры.",
      "price": "от 6 000 ₸",
      "time": "Срок: 45 мин",
      "warr": "Гарантия: 12 мес"
    },
    "sub-app-2-4": {
      "title": "Устранение засора",
      "desc": "Замена ТЭНа оттайки, плавкого предохранителя, таймера оттайки или вентилятора испарителя.",
      "price": "от 8 000 ₸",
      "time": "Срок: 1.5 часа",
      "warr": "Гарантия: 12 мес"
    },
    "sub-app-2-5": {
      "title": "Ремонт модуля управления",
      "desc": "Профессиональные услуги: Ремонт модуля управления в Алматы и по всему Казахстану. Быстрый выезд, квалифицированные специалисты и гарантия качества.",
      "price": "Договорная цена",
      "time": "Выезд: 45 мин",
      "warr": "Гарантия: 12 мес"
    },
    "sub-app-2-6": {
      "title": "Замена заливного/сливного клапана",
      "desc": "Профессиональные услуги: Замена заливного/сливного клапана в Алматы и по всему Казахстану. Быстрый выезд, квалифицированные специалисты и гарантия качества.",
      "price": "Договорная цена",
      "time": "Выезд: 45 мин",
      "warr": "Гарантия: 12 мес"
    },
    "sub-app-2-7": {
      "title": "Устранение протечки",
      "desc": "Профессиональные услуги: Устранение протечки в Алматы и по всему Казахстану. Быстрый выезд, квалифицированные специалисты и гарантия качества.",
      "price": "Договорная цена",
      "time": "Выезд: 45 мин",
      "warr": "Гарантия: 12 мес"
    },
    "sub-app-3-1": {
      "title": "Диагностика",
      "desc": "Диагностика и ремонт стиральных машин на дому. Замена запчастей, устранение течи, ремонт электроники.",
      "price": "от 5 000 ₸",
      "time": "Срок: 1-3 часа",
      "warr": "Гарантия: 12 мес"
    },
    "sub-app-3-2": {
      "title": "Заправка фреоном",
      "desc": "Срочный ремонт бытовых и торговых холодильников. Замена компрессоров, заправка хладагентом, ремонт плат.",
      "price": "от 6 000 ₸",
      "time": "Срок: 1-3 часа",
      "warr": "Гарантия: 12 мес"
    },
    "sub-app-3-3": {
      "title": "Замена компрессора",
      "desc": "Устранение засоров, ремонт нагревателей, циркуляционных насосов, замена датчиков уровня воды.",
      "price": "от 7 000 ₸",
      "time": "Срок: 1-2 часа",
      "warr": "Гарантия: 12 мес"
    },
    "sub-app-3-4": {
      "title": "Замена терморегулятора",
      "desc": "Профессиональные услуги: Замена терморегулятора в Алматы и по всему Казахстану. Быстрый выезд, квалифицированные специалисты и гарантия качества.",
      "price": "Договорная цена",
      "time": "Выезд: 45 мин",
      "warr": "Гарантия: 12 мес"
    },
    "sub-app-3-5": {
      "title": "Замена уплотнительной резины",
      "desc": "Профессиональные услуги: Замена уплотнительной резины в Алматы и по всему Казахстану. Быстрый выезд, квалифицированные специалисты и гарантия качества.",
      "price": "Договорная цена",
      "time": "Выезд: 45 мин",
      "warr": "Гарантия: 12 мес"
    },
    "sub-app-3-6": {
      "title": "Ремонт системы No Frost",
      "desc": "Профессиональные услуги: Ремонт системы No Frost в Алматы и по всему Казахстану. Быстрый выезд, квалифицированные специалисты и гарантия качества.",
      "price": "Договорная цена",
      "time": "Выезд: 45 мин",
      "warr": "Гарантия: 12 мес"
    },
    "sub-app-3-7": {
      "title": "Замена платы управления",
      "desc": "Профессиональные услуги: Замена платы управления в Алматы и по всему Казахстану. Быстрый выезд, квалифицированные специалисты и гарантия качества.",
      "price": "Договорная цена",
      "time": "Выезд: 45 мин",
      "warr": "Гарантия: 12 мес"
    },
    "sub-app-4-1": {
      "title": "Диагностика",
      "desc": "Монтаж кухонной вытяжки на стену или в шкафчик, подключение к вентиляционному каналу воздуховодом.",
      "price": "от 6 000 ₸",
      "time": "Срок: 1-1.5 часа",
      "warr": "Гарантия: 12 мес"
    },
    "sub-app-4-2": {
      "title": "Заправка фреоном",
      "desc": "Замена мотора вытяжки, ремонт кнопочных переключателей или электронных плат управления, замена подсветки.",
      "price": "от 5 000 ₸",
      "time": "Срок: 1 час",
      "warr": "Гарантия: 12 мес"
    },
    "sub-app-4-3": {
      "title": "Чистка и обслуживание",
      "desc": "Профессиональные услуги: Чистка и обслуживание в Алматы и по всему Казахстану. Быстрый выезд, квалифицированные специалисты и гарантия качества.",
      "price": "Договорная цена",
      "time": "Выезд: 45 мин",
      "warr": "Гарантия: 12 мес"
    },
    "sub-app-4-4": {
      "title": "Установка / монтаж",
      "desc": "Профессиональные услуги: Установка / монтаж в Алматы и по всему Казахстану. Быстрый выезд, квалифицированные специалисты и гарантия качества.",
      "price": "Договорная цена",
      "time": "Выезд: 45 мин",
      "warr": "Гарантия: 12 мес"
    },
    "sub-app-4-5": {
      "title": "Демонтаж",
      "desc": "Профессиональные услуги: Демонтаж в Алматы и по всему Казахстану. Быстрый выезд, квалифицированные специалисты и гарантия качества.",
      "price": "Договорная цена",
      "time": "Выезд: 45 мин",
      "warr": "Гарантия: 12 мес"
    },
    "sub-app-4-6": {
      "title": "Ремонт платы",
      "desc": "Профессиональные услуги: Ремонт платы в Алматы и по всему Казахстану. Быстрый выезд, квалифицированные специалисты и гарантия качества.",
      "price": "Договорная цена",
      "time": "Выезд: 45 мин",
      "warr": "Гарантия: 12 мес"
    },
    "sub-app-4-7": {
      "title": "Замена компрессора",
      "desc": "Профессиональные услуги: Замена компрессора в Алматы и по всему Казахстану. Быстрый выезд, квалифицированные специалисты и гарантия качества.",
      "price": "Договорная цена",
      "time": "Выезд: 45 мин",
      "warr": "Гарантия: 12 мес"
    },
    "sub-app-5-1": {
      "title": "Диагностика",
      "desc": "Стандартный и нестандартный монтаж сплит-систем любой мощности. Использование качественной медной трубы.",
      "price": "от 18 000 ₸",
      "time": "Срок: 2-3 часа",
      "warr": "Гарантия: 12 мес"
    },
    "sub-app-5-2": {
      "title": "Замена ТЭНа",
      "desc": "Ремонт компрессора, замена четырехходового клапана, ремонт и пайка медных трасс, устранение утечек фреона.",
      "price": "от 8 000 ₸",
      "time": "Срок: 1-2 часа",
      "warr": "Гарантия: 12 мес"
    },
    "sub-app-5-3": {
      "title": "Замена ремня",
      "desc": "Аккуратный демонтаж блоков с сохранением фреона в компрессоре кондиционера для последующей установки.",
      "price": "от 8 000 ₸",
      "time": "Срок: 45 мин",
      "warr": "Гарантия: - "
    },
    "sub-app-5-4": {
      "title": "Чистка фильтров и каналов",
      "desc": "Профессиональные услуги: Чистка фильтров и каналов в Алматы и по всему Казахстану. Быстрый выезд, квалифицированные специалисты и гарантия качества.",
      "price": "Договорная цена",
      "time": "Выезд: 45 мин",
      "warr": "Гарантия: 12 мес"
    },
    "sub-app-5-5": {
      "title": "Ремонт модуля",
      "desc": "Профессиональные услуги: Ремонт модуля в Алматы и по всему Казахстану. Быстрый выезд, квалифицированные специалисты и гарантия качества.",
      "price": "Договорная цена",
      "time": "Выезд: 45 мин",
      "warr": "Гарантия: 12 мес"
    },
    "sub-app-5-6": {
      "title": "Замена подшипников",
      "desc": "Профессиональные услуги: Замена подшипников в Алматы и по всему Казахстану. Быстрый выезд, квалифицированные специалисты и гарантия качества.",
      "price": "Договорная цена",
      "time": "Выезд: 45 мин",
      "warr": "Гарантия: 12 мес"
    },
    "sub-app-6-1": {
      "title": "Диагностика",
      "desc": "Сварка водопроводных труб, стояков отопления, газовых труб аттестованными сварщиками. Гарантия прочности шва.",
      "price": "от 5 000 ₸",
      "time": "Срок: 1-2 часа",
      "warr": "Гарантия: 24 мес"
    },
    "sub-app-6-2": {
      "title": "Замена ТЭНа духовки",
      "desc": "Ремонт и замена изношенных или сорванных петель гаражных ворот, калиток. Приварка прочных петель с подшипниками.",
      "price": "от 4 000 ₸",
      "time": "Срок: 40 мин",
      "warr": "Гарантия: 12 мес"
    },
    "sub-app-6-3": {
      "title": "Замена конфорки",
      "desc": "Мелкий и крупный ремонт металлических изделий электросваркой на выезде со своим генератором.",
      "price": "договорная",
      "time": "Срок: 1-3 часа",
      "warr": "Гарантия: 12 мес"
    },
    "sub-app-6-4": {
      "title": "Замена термостата",
      "desc": "Профессиональные услуги: Замена термостата в Алматы и по всему Казахстану. Быстрый выезд, квалифицированные специалисты и гарантия качества.",
      "price": "Договорная цена",
      "time": "Выезд: 45 мин",
      "warr": "Гарантия: 12 мес"
    },
    "sub-app-6-5": {
      "title": "Ремонт переключателей",
      "desc": "Профессиональные услуги: Ремонт переключателей в Алматы и по всему Казахстану. Быстрый выезд, квалифицированные специалисты и гарантия качества.",
      "price": "Договорная цена",
      "time": "Выезд: 45 мин",
      "warr": "Гарантия: 12 мес"
    },
    "sub-app-6-6": {
      "title": "Замена стекла дверцы",
      "desc": "Профессиональные услуги: Замена стекла дверцы в Алматы и по всему Казахстану. Быстрый выезд, квалифицированные специалисты и гарантия качества.",
      "price": "Договорная цена",
      "time": "Выезд: 45 мин",
      "warr": "Гарантия: 12 мес"
    },
    "sub-app-7-1": {
      "title": "Диагностика",
      "desc": "Изготовление металлических навесов для автомобилей, зон отдыха из поликарбоната, профнастила, металлочерепицы.",
      "price": "от 15 000 ₸/кв.м",
      "time": "Срок: 3-5 дней",
      "warr": "Гарантия: 36 мес"
    },
    "sub-app-7-2": {
      "title": "Замена стеклокерамики",
      "desc": "Установка заборов из профлиста, сетки-рабицы, металлического штакетника, 3D-панелей. Быстро и надежно.",
      "price": "от 5 000 ₸/п.м",
      "time": "Срок: 2-4 дня",
      "warr": "Гарантия: 24 мес"
    },
    "sub-app-7-3": {
      "title": "Ремонт силового модуля",
      "desc": "Изготовление прочных распашных и глухих оконных решеток, дутых решеток, кованых изделий безопасности.",
      "price": "от 8 000 ₸/кв.м",
      "time": "Срок: 2-3 дня",
      "warr": "Гарантия: 36 мес"
    },
    "sub-app-7-4": {
      "title": "Замена катушки индукции",
      "desc": "Изготовление и монтаж качественных металлических дверей для квартир, тамбуров, гаражей. Усиленная конструкция.",
      "price": "от 45 000 ₸",
      "time": "Срок: 3-4 дня",
      "warr": "Гарантия: 24 мес"
    },
    "sub-app-7-5": {
      "title": "Замена сенсорной панели",
      "desc": "Профессиональные услуги: Замена сенсорной панели в Алматы и по всему Казахстану. Быстрый выезд, квалифицированные специалисты и гарантия качества.",
      "price": "Договорная цена",
      "time": "Выезд: 45 мин",
      "warr": "Гарантия: 12 мес"
    },
    "sub-app-7-6": {
      "title": "Устранение ошибок (коды E)",
      "desc": "Профессиональные услуги: Устранение ошибок (коды E) в Алматы и по всему Казахстану. Быстрый выезд, квалифицированные специалисты и гарантия качества.",
      "price": "Договорная цена",
      "time": "Выезд: 45 мин",
      "warr": "Гарантия: 12 мес"
    },
    "sub-app-8-1": {
      "title": "Диагностика",
      "desc": "Замена старых, монтаж и перенос розеток и выключателей на новые места, штробление стен под кабель.",
      "price": "от 1 000 ₸/шт",
      "time": "Срок: 20 мин",
      "warr": "Гарантия: 12 мес"
    },
    "sub-app-8-2": {
      "title": "Замена двигателя",
      "desc": "Сборка, надежное крепление и подключение любых люстр, точечных светильников, светодиодных лент, бра.",
      "price": "от 3 000 ₸/шт",
      "time": "Срок: 30 мин",
      "warr": "Гарантия: 12 мес"
    },
    "sub-app-8-3": {
      "title": "Ремонт/замена подсветки",
      "desc": "Диагностика электропроводки спецприборами, поиск места обрыва или замыкания кабеля, локальное устранение.",
      "price": "от 5 000 ₸",
      "time": "Срок: 1-2 часа",
      "warr": "Гарантия: 12 мес"
    },
    "sub-app-8-4": {
      "title": "Чистка и обслуживание",
      "desc": "Замена старых пробок, установка автоматов (УЗО), сборка и модернизация электрощитов.",
      "price": "от 2 000 ₸/шт",
      "time": "Срок: 30 мин",
      "warr": "Гарантия: 12 мес"
    },
    "sub-app-8-5": {
      "title": "Замена фильтров",
      "desc": "Профессиональные услуги: Замена фильтров в Алматы и по всему Казахстану. Быстрый выезд, квалифицированные специалисты и гарантия качества.",
      "price": "Договорная цена",
      "time": "Выезд: 45 мин",
      "warr": "Гарантия: 12 мес"
    },
    "sub-app-8-6": {
      "title": "Ремонт кнопок/электроники",
      "desc": "Профессиональные услуги: Ремонт кнопок/электроники в Алматы и по всему Казахстану. Быстрый выезд, квалифицированные специалисты и гарантия качества.",
      "price": "Договорная цена",
      "time": "Выезд: 45 мин",
      "warr": "Гарантия: 12 мес"
    }
  }
}